<stg><name>honeybee</name>


<trans_list>

<trans id="26" from="1" to="2">
<condition id="-1">
<or_exp><and_exp></and_exp></or_exp>
</condition>
</trans>
</trans_list>



<state_list>

<state id="1" st_id="1">

<operation id="3" st_id="1" stage="1" lat="1">
<core>NULL</core>
<MemPortIdVec></MemPortIdVec>
<condition id="-1">
<or_exp><and_exp></and_exp></or_exp>
</condition>

<Node id="15" bw="32" op_0_bw="32" op_1_bw="32">
<![CDATA[
:8  %edge_p2_z_read = call float @_ssdm_op_Read.ap_auto.float(float %edge_p2_z)

]]></Node>
<StgValue><ssdm name="edge_p2_z_read"/></StgValue>
</operation>

<operation id="4" st_id="1" stage="1" lat="1">
<core>NULL</core>
<MemPortIdVec></MemPortIdVec>
<condition id="-1">
<or_exp><and_exp></and_exp></or_exp>
</condition>

<Node id="16" bw="32" op_0_bw="32" op_1_bw="32">
<![CDATA[
:9  %edge_p2_y_read = call float @_ssdm_op_Read.ap_auto.float(float %edge_p2_y)

]]></Node>
<StgValue><ssdm name="edge_p2_y_read"/></StgValue>
</operation>

<operation id="5" st_id="1" stage="1" lat="1">
<core>NULL</core>
<MemPortIdVec></MemPortIdVec>
<condition id="-1">
<or_exp><and_exp></and_exp></or_exp>
</condition>

<Node id="17" bw="32" op_0_bw="32" op_1_bw="32">
<![CDATA[
:10  %edge_p2_x_read = call float @_ssdm_op_Read.ap_auto.float(float %edge_p2_x)

]]></Node>
<StgValue><ssdm name="edge_p2_x_read"/></StgValue>
</operation>

<operation id="6" st_id="1" stage="1" lat="1">
<core>NULL</core>
<MemPortIdVec></MemPortIdVec>
<condition id="-1">
<or_exp><and_exp></and_exp></or_exp>
</condition>

<Node id="18" bw="32" op_0_bw="32" op_1_bw="32">
<![CDATA[
:11  %edge_p1_z_read = call float @_ssdm_op_Read.ap_auto.float(float %edge_p1_z)

]]></Node>
<StgValue><ssdm name="edge_p1_z_read"/></StgValue>
</operation>

<operation id="7" st_id="1" stage="1" lat="1">
<core>NULL</core>
<MemPortIdVec></MemPortIdVec>
<condition id="-1">
<or_exp><and_exp></and_exp></or_exp>
</condition>

<Node id="19" bw="32" op_0_bw="32" op_1_bw="32">
<![CDATA[
:12  %edge_p1_y_read = call float @_ssdm_op_Read.ap_auto.float(float %edge_p1_y)

]]></Node>
<StgValue><ssdm name="edge_p1_y_read"/></StgValue>
</operation>

<operation id="8" st_id="1" stage="1" lat="1">
<core>NULL</core>
<MemPortIdVec></MemPortIdVec>
<condition id="-1">
<or_exp><and_exp></and_exp></or_exp>
</condition>

<Node id="20" bw="32" op_0_bw="32" op_1_bw="32">
<![CDATA[
:13  %edge_p1_x_read = call float @_ssdm_op_Read.ap_auto.float(float %edge_p1_x)

]]></Node>
<StgValue><ssdm name="edge_p1_x_read"/></StgValue>
</operation>

<operation id="9" st_id="1" stage="2" lat="2">
<core></core>
<MemPortIdVec></MemPortIdVec>
<condition id="-1">
<or_exp><and_exp></and_exp></or_exp>
</condition>

<Node id="21" bw="64" op_0_bw="64" op_1_bw="32" op_2_bw="32" op_3_bw="32" op_4_bw="32" op_5_bw="32" op_6_bw="32">
<![CDATA[
:14  %collisions_z = call fastcc i64 @checkAxis.2(float %edge_p1_x_read, float %edge_p1_y_read, float %edge_p1_z_read, float %edge_p2_x_read, float %edge_p2_y_read, float %edge_p2_z_read)

]]></Node>
<StgValue><ssdm name="collisions_z"/></StgValue>
</operation>

<operation id="10" st_id="1" stage="2" lat="2">
<core></core>
<MemPortIdVec></MemPortIdVec>
<condition id="-1">
<or_exp><and_exp></and_exp></or_exp>
</condition>

<Node id="22" bw="64" op_0_bw="64" op_1_bw="32" op_2_bw="32" op_3_bw="32" op_4_bw="32" op_5_bw="32" op_6_bw="32">
<![CDATA[
:15  %collisions_y = call fastcc i64 @checkAxis.0(float %edge_p1_x_read, float %edge_p1_z_read, float %edge_p1_y_read, float %edge_p2_x_read, float %edge_p2_z_read, float %edge_p2_y_read)

]]></Node>
<StgValue><ssdm name="collisions_y"/></StgValue>
</operation>

<operation id="11" st_id="1" stage="2" lat="2">
<core></core>
<MemPortIdVec></MemPortIdVec>
<condition id="-1">
<or_exp><and_exp></and_exp></or_exp>
</condition>

<Node id="23" bw="64" op_0_bw="64" op_1_bw="32" op_2_bw="32" op_3_bw="32" op_4_bw="32" op_5_bw="32" op_6_bw="32">
<![CDATA[
:16  %collisions_x = call fastcc i64 @checkAxis.1(float %edge_p1_z_read, float %edge_p1_y_read, float %edge_p1_x_read, float %edge_p2_z_read, float %edge_p2_y_read, float %edge_p2_x_read)

]]></Node>
<StgValue><ssdm name="collisions_x"/></StgValue>
</operation>
</state>

<state id="2" st_id="2">

<operation id="12" st_id="2" stage="1" lat="1">
<core>NULL</core>
<MemPortIdVec></MemPortIdVec>
<condition id="-1">
<or_exp><and_exp></and_exp></or_exp>
</condition>

<Node id="7" bw="0" op_0_bw="0" op_1_bw="32">
<![CDATA[
:0  call void (...)* @_ssdm_op_SpecBitsMap(float %edge_p1_x), !map !39

]]></Node>
<StgValue><ssdm name="specbitsmap_ln0"/></StgValue>
</operation>

<operation id="13" st_id="2" stage="1" lat="1">
<core>NULL</core>
<MemPortIdVec></MemPortIdVec>
<condition id="-1">
<or_exp><and_exp></and_exp></or_exp>
</condition>

<Node id="8" bw="0" op_0_bw="0" op_1_bw="32">
<![CDATA[
:1  call void (...)* @_ssdm_op_SpecBitsMap(float %edge_p1_y), !map !45

]]></Node>
<StgValue><ssdm name="specbitsmap_ln0"/></StgValue>
</operation>

<operation id="14" st_id="2" stage="1" lat="1">
<core>NULL</core>
<MemPortIdVec></MemPortIdVec>
<condition id="-1">
<or_exp><and_exp></and_exp></or_exp>
</condition>

<Node id="9" bw="0" op_0_bw="0" op_1_bw="32">
<![CDATA[
:2  call void (...)* @_ssdm_op_SpecBitsMap(float %edge_p1_z), !map !49

]]></Node>
<StgValue><ssdm name="specbitsmap_ln0"/></StgValue>
</operation>

<operation id="15" st_id="2" stage="1" lat="1">
<core>NULL</core>
<MemPortIdVec></MemPortIdVec>
<condition id="-1">
<or_exp><and_exp></and_exp></or_exp>
</condition>

<Node id="10" bw="0" op_0_bw="0" op_1_bw="32">
<![CDATA[
:3  call void (...)* @_ssdm_op_SpecBitsMap(float %edge_p2_x), !map !53

]]></Node>
<StgValue><ssdm name="specbitsmap_ln0"/></StgValue>
</operation>

<operation id="16" st_id="2" stage="1" lat="1">
<core>NULL</core>
<MemPortIdVec></MemPortIdVec>
<condition id="-1">
<or_exp><and_exp></and_exp></or_exp>
</condition>

<Node id="11" bw="0" op_0_bw="0" op_1_bw="32">
<![CDATA[
:4  call void (...)* @_ssdm_op_SpecBitsMap(float %edge_p2_y), !map !57

]]></Node>
<StgValue><ssdm name="specbitsmap_ln0"/></StgValue>
</operation>

<operation id="17" st_id="2" stage="1" lat="1">
<core>NULL</core>
<MemPortIdVec></MemPortIdVec>
<condition id="-1">
<or_exp><and_exp></and_exp></or_exp>
</condition>

<Node id="12" bw="0" op_0_bw="0" op_1_bw="32">
<![CDATA[
:5  call void (...)* @_ssdm_op_SpecBitsMap(float %edge_p2_z), !map !61

]]></Node>
<StgValue><ssdm name="specbitsmap_ln0"/></StgValue>
</operation>

<operation id="18" st_id="2" stage="1" lat="1">
<core>NULL</core>
<MemPortIdVec></MemPortIdVec>
<condition id="-1">
<or_exp><and_exp></and_exp></or_exp>
</condition>

<Node id="13" bw="0" op_0_bw="0" op_1_bw="64">
<![CDATA[
:6  call void (...)* @_ssdm_op_SpecBitsMap(i64 0) nounwind, !map !65

]]></Node>
<StgValue><ssdm name="specbitsmap_ln0"/></StgValue>
</operation>

<operation id="19" st_id="2" stage="1" lat="1">
<core>NULL</core>
<MemPortIdVec></MemPortIdVec>
<condition id="-1">
<or_exp><and_exp></and_exp></or_exp>
</condition>

<Node id="14" bw="0" op_0_bw="0" op_1_bw="0">
<![CDATA[
:7  call void (...)* @_ssdm_op_SpecTopModule([9 x i8]* @honeybee_str) nounwind

]]></Node>
<StgValue><ssdm name="spectopmodule_ln0"/></StgValue>
</operation>

<operation id="20" st_id="2" stage="1" lat="2">
<core></core>
<MemPortIdVec></MemPortIdVec>
<condition id="-1">
<or_exp><and_exp></and_exp></or_exp>
</condition>

<Node id="21" bw="64" op_0_bw="64" op_1_bw="32" op_2_bw="32" op_3_bw="32" op_4_bw="32" op_5_bw="32" op_6_bw="32">
<![CDATA[
:14  %collisions_z = call fastcc i64 @checkAxis.2(float %edge_p1_x_read, float %edge_p1_y_read, float %edge_p1_z_read, float %edge_p2_x_read, float %edge_p2_y_read, float %edge_p2_z_read)

]]></Node>
<StgValue><ssdm name="collisions_z"/></StgValue>
</operation>

<operation id="21" st_id="2" stage="1" lat="2">
<core></core>
<MemPortIdVec></MemPortIdVec>
<condition id="-1">
<or_exp><and_exp></and_exp></or_exp>
</condition>

<Node id="22" bw="64" op_0_bw="64" op_1_bw="32" op_2_bw="32" op_3_bw="32" op_4_bw="32" op_5_bw="32" op_6_bw="32">
<![CDATA[
:15  %collisions_y = call fastcc i64 @checkAxis.0(float %edge_p1_x_read, float %edge_p1_z_read, float %edge_p1_y_read, float %edge_p2_x_read, float %edge_p2_z_read, float %edge_p2_y_read)

]]></Node>
<StgValue><ssdm name="collisions_y"/></StgValue>
</operation>

<operation id="22" st_id="2" stage="1" lat="2">
<core></core>
<MemPortIdVec></MemPortIdVec>
<condition id="-1">
<or_exp><and_exp></and_exp></or_exp>
</condition>

<Node id="23" bw="64" op_0_bw="64" op_1_bw="32" op_2_bw="32" op_3_bw="32" op_4_bw="32" op_5_bw="32" op_6_bw="32">
<![CDATA[
:16  %collisions_x = call fastcc i64 @checkAxis.1(float %edge_p1_z_read, float %edge_p1_y_read, float %edge_p1_x_read, float %edge_p2_z_read, float %edge_p2_y_read, float %edge_p2_x_read)

]]></Node>
<StgValue><ssdm name="collisions_x"/></StgValue>
</operation>

<operation id="23" st_id="2" stage="1" lat="1">
<core>LogicGate</core>
<MemPortIdVec></MemPortIdVec>
<condition id="-1">
<or_exp><and_exp></and_exp></or_exp>
</condition>

<Node id="24" bw="64" op_0_bw="64" op_1_bw="64">
<![CDATA[
:17  %or_ln164 = or i64 %collisions_z, %collisions_x

]]></Node>
<StgValue><ssdm name="or_ln164"/></StgValue>
</operation>

<operation id="24" st_id="2" stage="1" lat="1">
<core>LogicGate</core>
<MemPortIdVec></MemPortIdVec>
<condition id="-1">
<or_exp><and_exp></and_exp></or_exp>
</condition>

<Node id="25" bw="64" op_0_bw="64" op_1_bw="64">
<![CDATA[
:18  %collisions = or i64 %or_ln164, %collisions_y

]]></Node>
<StgValue><ssdm name="collisions"/></StgValue>
</operation>

<operation id="25" st_id="2" stage="1" lat="1">
<core>NULL</core>
<MemPortIdVec></MemPortIdVec>
<condition id="-1">
<or_exp><and_exp></and_exp></or_exp>
</condition>

<Node id="26" bw="0" op_0_bw="64">
<![CDATA[
:19  ret i64 %collisions

]]></Node>
<StgValue><ssdm name="ret_ln165"/></StgValue>
</operation>
</state>
</state_list>


<ports>
</ports>


<dataflows>
</dataflows>


</stg>
